{
    "data": {
        "articles" :[
            {
                "articleId": 1,
                "authorPortrait": "",
                "author": "小林",
                "title": "你所不知道额JavaScript",
                "content": "你所不知道额JavaScript你所不知道额JavaScript你所不知道额JavaScript你所不知道额JavaScript你所不知道额JavaScript你所不知道额JavaScript"
            },
            {
                "articleId": 2,
                "authorPortrait": "",
                "author": "小林",
                "title": "你所不知道额JavaScript",
                "content": "你所不知道额JavaScript你所不知道额JavaScript你所不知道额JavaScript你所不知道额JavaScript你所不知道额JavaScript你所不知道额JavaScript"
            },
            {
                "articleId": 3,
                "authorPortrait": "",
                "author": "小林",
                "title": "你所不知道额JavaScript",
                "content": "你所不知道额JavaScript你所不知道额JavaScript你所不知道额JavaScript你所不知道额JavaScript你所不知道额JavaScript你所不知道额JavaScript"
            },
            {
                "articleId": 4,
                "authorPortrait": "",
                "author": "小林",
                "title": "你所不知道额JavaScript",
                "content": "你所不知道额JavaScript你所不知道额JavaScript你所不知道额JavaScript你所不知道额JavaScript你所不知道额JavaScript你所不知道额JavaScript"
            },
            {
                "articleId": 5,
                "authorPortrait": "",
                "author": "小林",
                "title": "你所不知道额JavaScript",
                "content": "你所不知道额JavaScript你所不知道额JavaScript你所不知道额JavaScript你所不知道额JavaScript你所不知道额JavaScript你所不知道额JavaScript"
            }
        ]
    }
}